bitstruct/__init__.py
bitstruct/bitstream.c
bitstruct/bitstream.h
bitstruct/c.c
bitstruct/c.cpython-311-i386-linux-gnu.so
bitstruct-8.21.0.dist-info/METADATA
bitstruct-8.21.0.dist-info/WHEEL
bitstruct-8.21.0.dist-info/top_level.txt
bitstruct-8.21.0.dist-info/RECORD
bitstruct-8.21.0.dist-info/licenses/LICENSE
